README.md
openrazer_effects
setup.cfg
setup.py
openrazer/__init__.py
openrazer/client/__init__.py
openrazer/client/constants.py
openrazer/client/debug.py
openrazer/client/device.py
openrazer/client/fx.py
openrazer/client/macro.py
openrazer/client/devices/__init__.py
openrazer/client/devices/firefly.py
openrazer/client/devices/keyboard.py
openrazer/client/devices/mice.py
openrazer_daemon/__init__.py
openrazer_daemon/daemon.py
openrazer_daemon/device.py
openrazer_daemon/keyboard.py
openrazer_daemon/dbus_services/__init__.py
openrazer_daemon/dbus_services/service.py
openrazer_daemon/dbus_services/dbus_methods/__init__.py
openrazer_daemon/dbus_services/dbus_methods/all.py
openrazer_daemon/dbus_services/dbus_methods/bw2013.py
openrazer_daemon/dbus_services/dbus_methods/chroma_keyboard.py
openrazer_daemon/dbus_services/dbus_methods/deathadder_chroma.py
openrazer_daemon/dbus_services/dbus_methods/kraken.py
openrazer_daemon/dbus_services/dbus_methods/macro.py
openrazer_daemon/dbus_services/dbus_methods/mamba.py
openrazer_daemon/dbus_services/dbus_methods/mug.py
openrazer_daemon/dbus_services/dbus_methods/nagahex.py
openrazer_daemon/dbus_services/dbus_methods/nagahexv2.py
openrazer_daemon/dbus_services/dbus_methods/tartarus.py
openrazer_daemon/hardware/__init__.py
openrazer_daemon/hardware/core.py
openrazer_daemon/hardware/device_base.py
openrazer_daemon/hardware/headsets.py
openrazer_daemon/hardware/keyboards.py
openrazer_daemon/hardware/mouse.py
openrazer_daemon/hardware/mouse_mat.py
openrazer_daemon/hardware/mug.py
openrazer_daemon/misc/__init__.py
openrazer_daemon/misc/battery_notifier.py
openrazer_daemon/misc/effect_sync.py
openrazer_daemon/misc/key_event_management.py
openrazer_daemon/misc/macro.py
openrazer_daemon/misc/ripple_effect.py
openrazer_daemon/misc/screensaver_monitor.py
openrazer_effects.egg-info/PKG-INFO
openrazer_effects.egg-info/SOURCES.txt
openrazer_effects.egg-info/dependency_links.txt
openrazer_effects.egg-info/requires.txt
openrazer_effects.egg-info/top_level.txt
openrazer_effects.egg-info/zip-safe
ore/__init__.py
ore/cli.py
ore/audio/__init__.py
ore/audio/capture.py
ore/core/__init__.py
ore/core/effects.py
ore/core/program.py
ore/core/utils.py
ore/effects/__init__.py
