Metadata-Version: 1.2
Name: openrazer-effects
Version: 1.0.8
Summary: Effects for OpenRazer
Home-page: https://github.com/explodes/openrazer_effects
Author: Evan Leis
Author-email: UNKNOWN
License: GPLv2
Platform: UNKNOWN
Requires-Python: >=3.5
